xiyan_table_mcp_server/__init__.py
xiyan_table_mcp_server/__main__.py
xiyan_table_mcp_server/server.py
xiyan_table_mcp_server-0.9.0.dist-info/licenses/LICENSE.txt
xiyan_table_mcp_server-0.9.0.dist-info/METADATA
xiyan_table_mcp_server-0.9.0.dist-info/WHEEL
xiyan_table_mcp_server-0.9.0.dist-info/entry_points.txt
xiyan_table_mcp_server-0.9.0.dist-info/top_level.txt
xiyan_table_mcp_server-0.9.0.dist-info/RECORD
