Metadata-Version: 2.4
Name: xiyan_table_mcp_server
Version: 0.9.0
Summary: A Model Context Protocol (MCP) server that allows AI assistants to display table contents and perform natural language queries.
Home-page: https://github.com/yourusername/xiyan_table_mcp_server
Author: Shixiaorong
Author-email: Shixiaorong <shixiaorong.sxr@alibaba-inc.com>
License-Expression: MIT
Project-URL: Homepage, https://github.com/yourusername/xiyan_table_mcp_server
Classifier: Development Status :: 3 - Alpha
Classifier: Intended Audience :: Developers
Classifier: Programming Language :: Python :: 3.10
Classifier: Programming Language :: Python :: 3.11
Requires-Python: >=3.10
License-File: LICENSE.txt
Requires-Dist: httpx>=0.28.1
Requires-Dist: mcp[cli]>=1.2.0
Requires-Dist: fastapi>=0.109.0
Requires-Dist: uvicorn>=0.27.0
Requires-Dist: pydantic>=2.0.0
Requires-Dist: pandas>=2.0.0
Requires-Dist: pyyaml>=6.0.0
Requires-Dist: openai
Requires-Dist: dashscope
Dynamic: author
Dynamic: home-page
Dynamic: license-file
Dynamic: requires-python
